acfr/__init__.py
acfr/acfr.py
acfr-0.0.1.dist-info/LICENSE
acfr-0.0.1.dist-info/METADATA
acfr-0.0.1.dist-info/WHEEL
acfr-0.0.1.dist-info/top_level.txt
acfr-0.0.1.dist-info/RECORD
