Metadata-Version: 2.1
Name: acfr
Version: 0.0.1
Summary: Angle Correction for Rotators
Home-page: https://github.com/bmehlhorn/acfr
Author: Börge Mehlhorn
Author-email: b.mehlhorn@ifw-dresden.de
License: UNKNOWN
Project-URL: Bug Tracker, https://github.com/bmehlhorn/acfr/issues
Platform: UNKNOWN
Classifier: Programming Language :: Python :: 3
Classifier: License :: OSI Approved :: GNU General Public License v3 (GPLv3)
Classifier: Operating System :: OS Independent
Requires-Python: >=3.9
License-File: LICENSE
